dataserv/Farmer.py
dataserv/Validator.py
dataserv/__init__.py
dataserv/app.py
dataserv/config.py
dataserv/run.py
dataserv/version.py
dataserv/migrations/alembic.ini
dataserv/migrations/env.py
dataserv/migrations/script.py.mako
dataserv/migrations/versions/14d4ac0f0f1_.py
dataserv-2.2.13.dist-info/DESCRIPTION.rst
dataserv-2.2.13.dist-info/METADATA
dataserv-2.2.13.dist-info/RECORD
dataserv-2.2.13.dist-info/WHEEL
dataserv-2.2.13.dist-info/metadata.json
dataserv-2.2.13.dist-info/top_level.txt
tests/__init__.py
tests/test_App.py
tests/test_Farmer.py
tests/test_Validator.py
