Metadata-Version: 2.0
Name: dataserv
Version: 2.2.13
Summary: Federated server for getting, pushing, and auditing data on untrusted nodes.
Home-page: http://storj.io
Author: Shawn Wilkinson
Author-email: shawn+dataserv@storj.io
License: MIT
Download-URL: https://pypi.python.org/packages/3.4/d/dataserv/dataserv-2.2.13-py2.py3-none-any.whl
Platform: UNKNOWN
Classifier: Development Status :: 3 - Alpha
Classifier: Intended Audience :: Developers
Classifier: License :: OSI Approved :: MIT License
Classifier: Operating System :: OS Independent
Classifier: Programming Language :: Python
Classifier: Programming Language :: Python :: 2
Classifier: Programming Language :: Python :: 2.7
Classifier: Programming Language :: Python :: 3
Classifier: Programming Language :: Python :: 3.3
Classifier: Programming Language :: Python :: 3.4
Classifier: Topic :: Software Development :: Libraries :: Python Modules
Requires-Dist: Flask (==0.10.1)
Requires-Dist: Flask-Cache (==0.13.1)
Requires-Dist: Flask-Migrate (==1.5.1)
Requires-Dist: Flask-SQLAlchemy (==2.0)
Requires-Dist: RandomIO (==0.2.1)
Requires-Dist: btctxstore (==4.5.0)
Requires-Dist: gunicorn (==19.3.0)
Requires-Dist: partialhash (==1.1.0)
Requires-Dist: psycopg2
Requires-Dist: storjcore (==0.0.3)
